jyutping/__init__.py
jyutping/dictionary.py
jyutping/jyutping.py
jyutping/logger.py
jyutping/data/zidian_zhyue-ft-kfcd-yp-2013122.txt
jyutping-0.3.3.dist-info/METADATA
jyutping-0.3.3.dist-info/WHEEL
jyutping-0.3.3.dist-info/RECORD
