Metadata-Version: 2.1
Name: jyutping
Version: 0.3.3
Summary: Read the latest Real Python tutorials
Project-URL: Homepage, https://github.com/imdreamrunner/python-jyutping/
Author-email: Ivor Zhou <hello@ivorz.com>
License: MIT
Keywords: jyutping
Provides-Extra: dev
